{"chromox":{"tier":"OU","isNonstandard":null,"randomBattleMoves":["eruption","voltswitch","fireblast","flashcannon","protect"],"randomBattleLevel":72},"grasshole":{"tier":"LC","isNonstandard":null},"analgae":{"tier":"NFE","isNonstandard":null},"rectreem":{"tier":"NU","isNonstandard":null,"randomBattleMoves":["enema","earthquake","bulkup","stealthrock","rockslide","woodhammer","superpower"],"randomBattleLevel":84},"arabomb":{"tier":"LC","isNonstandard":null},"iguallah":{"tier":"NFE","isNonstandard":null},"lizakbar":{"tier":"UU","isNonstandard":null,"randomBattleMoves":["holyduty","fireblast","darkpulse","nastyplot","focusblast","willowisp"],"randomBattleLevel":84},"ejacasm":{"tier":"LC","isNonstandard":null},"hosajack":{"tier":"UU","isNonstandard":null},"condoom":{"tier":"OU","isNonstandard":null,"randomBattleMoves":["scald","softboiled","stickyweb","rapidspin","sludgebomb","icebeam"],"randomBattleLevel":76},"squirrap":{"tier":"LC","isNonstandard":null},"gampster":{"tier":"NU","isNonstandard":null,"randomBattleMoves":["boomburst","flamethrower","foulplay","uturn","nastyplot"],"randomBattleLevel":84},"kengeon":{"tier":"LC","isNonstandard":null},"frieden":{"tier":"NFE","isNonstandard":null},"corooster":{"tier":"RU","isNonstandard":null,"randomBattleMoves":["bravebird","roost","defog","closecombat","bulkup"],"randomBattleLevel":80},"curicrawl":{"tier":"LC","isNonstandard":null},"gutsicoon":{"tier":"NFE","isNonstandard":null},"gutsifly":{"tier":"RU","isNonstandard":null,"randomBattleMoves":["stickyweb","sleeppowder","uturn","defog","taunt","roost"],"randomBattleLevel":80},"larvades":{"tier":"LC","isNonstandard":null},"proboskito":{"tier":"RU","isNonstandard":null},"clovour":{"tier":"LC","isNonstandard":null},"chanolour":{"tier":"OU","isNonstandard":null,"randomBattleMoves":["ironhead","futababreak","superpower","uturn","rockslide"],"randomBattleLevel":76},"nauseon":{"tier":"LC","isNonstandard":null},"hazmate":{"tier":"NU","isNonstandard":null,"randomBattleMoves":["glare","gunkshot","bulkup","knockoff","drainpunch"],"randomBattleLevel":84},"ebolable":{"tier":"NU","isNonstandard":null,"randomBattleMoves":["sludgewave","darkpulse","focusblast","trick","flamethrower"],"randomBattleLevel":84},"pikotton":{"tier":"UU","isNonstandard":null,"randomBattleMoves":["thunderbolt","voltswitch","lactoseshot","stickyweb","surf","wish","protect"],"randomBattleLevel":80},"birdhouse":{"tier":"RU","isNonstandard":null,"randomBattleMoves":["softboiled","leechseed","bravebird","defog","stealthrock","uturn"],"randomBattleLevel":84},"lanshil":{"tier":"LC","isNonstandard":null},"middril":{"tier":"NFE","isNonstandard":null},"shurismash":{"tier":"RU","isNonstandard":null,"randomBattleMoves":["shellsmash","headsmash","meteormash","earthquake"],"randomBattleLevel":84},"maymay":{"tier":"LC","isNonstandard":null},"memenace":{"tier":"NU","isNonstandard":null,"randomBattleMoves":["milkdrink","meme","bodyslam","earthquake","bulkup"],"randomBattleLevel":84},"piguson":{"tier":"UU","isNonstandard":null,"randomBattleMoves":["riotshield","rapidspin","glare","slackoff","return"],"randomBattleLevel":80},"armando":{"tier":"LC","isNonstandard":null},"muscledude":{"tier":"NFE","isNonstandard":null},"tripecs":{"tier":"NU","isNonstandard":null,"randomBattleMoves":["superpower","knockoff","uturn","icepunch","thunderpunch"],"randomBattleLevel":84},"semdrop":{"tier":"LC","isNonstandard":null},"semrust":{"tier":"RU","isNonstandard":null},"furnazi":{"tier":"LC","isNonstandard":null},"finasoven":{"tier":"NU","isNonstandard":null,"randomBattleMoves":["trickroom","fireblast","powergem","earthpower","scald"],"randomBattleLevel":84},"troubait":{"tier":"LC","isNonstandard":null},"tulure":{"tier":"NFE","isNonstandard":null},"monstrap":{"tier":"UU","isNonstandard":null,"randomBattleMoves":["knockoff","uturn","stealthrock","liquidation","aquajet"],"randomBattleLevel":80},"pixila":{"tier":"LC","isNonstandard":null},"fairileon":{"tier":"RU","isNonstandard":null,"randomBattleMoves":["quiverdance","moonblast","bugbuzz","earthpower","roost"],"randomBattleLevel":84},"wedgard":{"tier":"LC","isNonstandard":null},"knokedge":{"tier":"NU","isNonstandard":null,"randomBattleMoves":["rapidspin","stealthrock","earthquake","knockoff","stoneedge","spikes"],"randomBattleLevel":84},"ribbizap":{"tier":"RU","isNonstandard":null,"randomBattleMoves":["tailglow","thunderbolt","icebeam","boomburst","energyball"],"randomBattleLevel":80},"elephas":{"tier":"RU","isNonstandard":null,"randomBattleMoves":["calmmind","psychic","earthpower","willowisp"],"randomBattleLevel":84},"seamapan":{"tier":"UUBL","isNonstandard":null,"randomBattleMoves":["lovelykiss","scald","waterspout","healbell","calmmind","icebeam"],"randomBattleLevel":80},"caroline":{"tier":"RU","isNonstandard":null,"randomBattleMoves":["bravebird","earthquake","swordsdance","closecombat","stoneedge"],"randomBattleLevel":84},"chompest":{"tier":"NFE","isNonstandard":null},"masdawg":{"tier":"NU","isNonstandard":null},"pasdawg":{"tier":"OU","isNonstandard":null,"randomBattleMoves":["bodyslam","ironhead","closecombat","uturn","earthquake","stealthrock"],"randomBattleLevel":80},"spanke":{"tier":"LC","isNonstandard":null},"anaconduke":{"tier":"NU","isNonstandard":null,"randomBattleMoves":["powerwhip","crosschop","coil","grasswhistle","rockslide"],"randomBattleLevel":84},"fishnism":{"tier":"LC","isNonstandard":null},"sjwhale":{"tier":"NU","isNonstandard":null,"randomBattleMoves":["slackoff","steameruption","psychicfangs","teleport","toxic"],"randomBattleLevel":84},"chezetta":{"tier":"LC","isNonstandard":null},"mozzamazel":{"tier":"OU","isNonstandard":null,"randomBattleMoves":["calmmind","drainingkiss","moonblast","flamethrower","willowisp"],"randomBattleLevel":76},"krokling":{"tier":"LC","isNonstandard":null},"krokizon":{"tier":"NU","isNonstandard":null,"randomBattleMoves":["stealthrock","earthquake","woodhammer","slackoff","headsmash","dragondance"],"randomBattleLevel":84},"conchilla":{"tier":"LC","isNonstandard":null},"haremit":{"tier":"NU","isNonstandard":null,"randomBattleMoves":["shellsmash","rockslide","bodyslam","earthquake","shoreup","crabhammer"],"randomBattleLevel":84},"coolcube":{"tier":"LC","isNonstandard":null},"tankube":{"tier":"NFE","isNonstandard":null},"fabkube":{"tier":"UU","isNonstandard":null,"randomBattleMoves":["calmmind","freezedry","icebeam","lactoseshot","moonblast","focusblast"],"randomBattleLevel":84},"smogaroben":{"tier":"LC","isNonstandard":null},"smoxilon":{"tier":"OU","isNonstandard":null,"randomBattleMoves":["spore","rapidspin","stickyweb","stealthrock","bravebird","taunt"],"randomBattleLevel":76},"machmona":{"tier":"UU","isNonstandard":null,"randomBattleMoves":["swordsdance","elbowdrop","superpower","spookout","machpunch"],"randomBattleLevel":80},"bacub":{"tier":"LC","isNonstandard":null},"urswine":{"tier":"NU","isNonstandard":null,"randomBattleMoves":["willowisp","firelash","softboiled","bodyslam","earthquake"],"randomBattleLevel":84},"moostatic":{"tier":"LC","isNonstandard":null},"mooshock":{"tier":"NU","isNonstandard":null,"randomBattleMoves":["volttackle","flareblitz","voltswitch","milkdrink","outrage"],"randomBattleLevel":84},"pretzely":{"tier":"OU","isNonstandard":null,"randomBattleMoves":["boomburst","focusblast","nastyplot","powergem"],"randomBattleLevel":80},"deemdow":{"tier":"LC","isNonstandard":null},"dowster":{"tier":"RU","isNonstandard":null,"randomBattleMoves":["spookout","shadowball","psychic","focusblast","trick"],"randomBattleLevel":80},"cheerly":{"tier":"LC","isNonstandard":null},"cheerific":{"tier":"NFE","isNonstandard":null},"mennopaws":{"tier":"RU","isNonstandard":null,"randomBattleMoves":["pixiepummel","earthquake","wish","swordsdance","substitute"],"randomBattleLevel":84},"caracold":{"tier":"LC","isNonstandard":null},"glacialynx":{"tier":"OU","isNonstandard":null,"randomBattleMoves":["icebeam","thunderbolt","voltswitch","grassknot","boltbeam"],"randomBattleLevel":76},"pengas":{"tier":"RUBL","isNonstandard":null,"randomBattleMoves":["boomburst","freezedry","fireblast","earthpower","trick"],"randomBattleLevel":76},"praeteur":{"tier":"LC","isNonstandard":null},"praestish":{"tier":"UU","isNonstandard":null,"randomBattleMoves":["uturn","scald","painsplit","toxic","icebeam"],"randomBattleLevel":76},"flowre":{"tier":"NU","isNonstandard":null},"florious":{"tier":"RUBL","isNonstandard":null,"randomBattleMoves":["darkpulse","sludgewave","focusblast","sleeppowder","calmmind"],"randomBattleLevel":84},"juarecito":{"tier":"LC","isNonstandard":null},"ponchito":{"tier":"NFE","isNonstandard":null},"somboludo":{"tier":"UU","isNonstandard":null,"randomBattleMoves":["mop","stealthrock","earthquake","meteormash","bulletpunch","slackoff"],"randomBattleLevel":76},"puppacti":{"tier":"LC","isNonstandard":null},"marionettl":{"tier":"RU","isNonstandard":null,"randomBattleMoves":["powerwhip","crabhammer","coil","leechlife","leechseed"],"randomBattleLevel":84},"tittai":{"tier":"LC","isNonstandard":null},"octai":{"tier":"RU","isNonstandard":null,"randomBattleMoves":["lactoseshot","milkdrink","scald","flamethrower","toxic"],"randomBattleLevel":80},"charagon":{"tier":"LC","isNonstandard":null},"hyletrack":{"tier":"RU","isNonstandard":null,"randomBattleMoves":["shiftgear","heatcrash","heavyslam","earthquake","extremespeed"],"randomBattleLevel":84},"euphoreal":{"tier":"LC","isNonstandard":null},"armowite":{"tier":"RU","isNonstandard":null,"randomBattleMoves":["owtheedge","1000folds","strengthsap","swordsdance","suckerpunch"],"randomBattleLevel":84},"praunch":{"tier":"LC","isNonstandard":null},"karawn":{"tier":"NU","isNonstandard":null},"mabster":{"tier":"OU","isNonstandard":null,"randomBattleMoves":["shellsmash","crabhammer","closecombat","earthquake","aquajet"],"randomBattleLevel":76},"tricient":{"tier":"LC","isNonstandard":null},"tricillion":{"tier":"NU","isNonstandard":null,"randomBattleMoves":["trickroom","headsmash","gyroball","earthquake","superpower"],"randomBattleLevel":84},"poizookie":{"tier":"LC","isNonstandard":null},"toxiraptor":{"tier":"RU","isNonstandard":null,"randomBattleMoves":["toxiravage","stoneedge","swordsdance","stompingtantrum","toxic"],"randomBattleLevel":80},"sabreck":{"tier":"LC","isNonstandard":null},"huntabre":{"tier":"OU","isNonstandard":null,"randomBattleMoves":["return","stoneedge","earthquake","stealthrock","knockoff"],"randomBattleLevel":80},"pyralink":{"tier":"RU","isNonstandard":null,"randomBattleMoves":["toke","flareblitz","clangingscales","earthquake"],"randomBattleLevel":80},"singlets":{"tier":"LC","isNonstandard":null},"dubus":{"tier":"NFE","isNonstandard":null},"tripsius":{"tier":"RU","isNonstandard":null,"randomBattleMoves":["checkem","volttackle","iciclespear","voltswitch","watershuriken"],"randomBattleLevel":84},"miasmer":{"tier":"LC","isNonstandard":null},"miasmortor":{"tier":"NU","isNonstandard":null,"randomBattleMoves":["reflect","lightscreen","taunt","voltswitch","spikes","gunkshot"],"randomBattleLevel":84},"cacademon":{"tier":"RU","isNonstandard":null,"randomBattleMoves":["earthquake","poisonjab","stealthrock","slackoff","toxic","clearsmog"],"randomBattleLevel":84},"hanginy":{"tier":"LC","isNonstandard":null},"chancer":{"tier":"NFE","isNonstandard":null,"randomBattleLevel":80},"unjoy":{"tier":"NU","isNonstandard":null,"randomBattleMoves":["willowisp","nightshade","softboiled","stealthrock","teleport"],"randomBattleLevel":84},"frosowl":{"tier":"LC","isNonstandard":null},"whizzard":{"tier":"OU","isNonstandard":null,"randomBattleMoves":["auroraveil","blizzard","uturn","roost","defog"],"randomBattleLevel":84},"drapillar":{"tier":"LC","isNonstandard":null},"caparagon":{"tier":"NFE","isNonstandard":null},"mantrake":{"tier":"UU","isNonstandard":null,"randomBattleMoves":["dragondance","megahorn","outrage","earthquake","leech life"],"randomBattleLevel":80},"ogrelord":{"tier":"NU","isNonstandard":null,"randomBattleMoves":["dragondance","knockoff","gunkshot","suckerpunch","earthquake"],"randomBattleLevel":84},"chantruth":{"tier":"UU","isNonstandard":null,"randomBattleMoves":["swindle","focusblast","earthpower","teleport","baddybad","sludgebomb","stealthrock"],"randomBattleLevel":84},"inbitween":{"tier":"LC","isNonstandard":null},"geigh":{"tier":"RU","isNonstandard":null,"randomBattleMoves":["aeroblast","airslash","moonblast","uturn","focusblast","heatwave"],"randomBattleLevel":84},"jarape":{"tier":"LC","isNonstandard":null},"spilefree":{"tier":"OU","isNonstandard":null,"randomBattleMoves":["voltswitch","shadowball","focusblast","thunderwave","destinybond","thunderbolt"],"randomBattleLevel":76},"bongecko":{"tier":"LC","isNonstandard":null},"mariguana":{"tier":"NFE","isNonstandard":null},"marleyzard":{"tier":"OU","isNonstandard":null,"randomBattleMoves":["toke","gigadrain","fireblast","earthpower","roost"],"randomBattleLevel":76},"ayylamo":{"tier":"NFE","isNonstandard":null},"smellox":{"tier":"OU","isNonstandard":null,"randomBattleMoves":["gunkshot","sing","uturn","highjumpkick","knockoff","toxic"],"randomBattleLevel":84},"chasumo":{"tier":"OU","isNonstandard":null,"randomBattleMoves":["highjumpkick","knockoff","ironhead","uturn","machpunch","slackoff","rapidspin"],"randomBattleLevel":84},"oilslam":{"tier":"LC","isNonstandard":null},"isissin":{"tier":"RU","isNonstandard":null,"randomBattleMoves":["softboiled","owtheedge","gunkshot","banefulbunker","earthquake","swordsdance","suckerpunch"],"randomBattleLevel":84},"stuffowl":{"tier":"LC","isNonstandard":null},"durkey":{"tier":"NFE","isNonstandard":null},"upchucken":{"tier":"OU","isNonstandard":null,"randomBattleMoves":["uturn","aeroblast","fireblast","roost","defog","hypervoice"],"randomBattleLevel":76},"dragun":{"tier":"LC","isNonstandard":null},"triggedon":{"tier":"NFE","isNonstandard":null},"cannonance":{"tier":"OU","isNonstandard":null,"randomBattleMoves":["dragonpulse","flashcannon","aurasphere","fireblast","darkpulse"],"randomBattleLevel":76},"evacycle":{"tier":"UU","isNonstandard":null,"randomBattleMoves":["shiftgear","heavyslam","zenheadbutt","flareblitz","earthquake"],"randomBattleLevel":80},"foryu":{"tier":"Uber","isNonstandard":null,"randomBattleMoves":["foryou","doubleironbash","knockoff","heatcrash","autotomize","closecombat"],"randomBattleLevel":72},"scytill":{"tier":"Uber","isNonstandard":null,"randomBattleMoves":["spookout","shadowsneak","heavyslam","uturn","earthquake"],"randomBattleLevel":72},"baddon":{"tier":"Uber","isNonstandard":null,"randomBattleMoves":["recover","dildocannon","coil","glare","gunkshot","earthquake"],"randomBattleLevel":72},"endranther":{"tier":"Uber","isNonstandard":null,"randomBattleMoves":["decaydrain","earthquake","explosion","strengthsap","knockoff"],"randomBattleLevel":72},"notridley":{"tier":"Uber","isNonstandard":null,"randomBattleMoves":["dragondance","acrobatics","earthquake","overheat","extremespeed","outrage"],"randomBattleLevel":72},"demiwaifu":{"tier":"Uber","isNonstandard":null,"randomBattleMoves":["calmmind","moonblast","drainingkiss","earthpower","fireblast","willowisp"],"randomBattleLevel":72},"reptyke":{"tier":"LC","isNonstandard":null},"rasclobber":{"tier":"NFE","isNonstandard":null},"batterex":{"tier":"RU","isNonstandard":null,"randomBattleMoves":["dragondance","dragonfist","closecombat","meteormash"],"randomBattleLevel":84},"faeriock":{"tier":"LC","isNonstandard":null},"sylvuin":{"tier":"NFE","isNonstandard":null},"oburonyxo":{"tier":"RU","isNonstandard":null,"randomBattleMoves":["erosionwave","earthpower","recover","stealthrock","teleport","glare"],"randomBattleLevel":84},"cloucat":{"tier":"LC","isNonstandard":null},"felimbus":{"tier":"NFE","isNonstandard":null},"deathorus":{"tier":"OU","isNonstandard":null,"randomBattleMoves":["knockoff","suckerpunch","stratoblade","swordsdance","sacredsword"],"randomBattleLevel":76},"knogoat":{"tier":"LC","isNonstandard":null},"knogrinyu":{"tier":"NU","isNonstandard":null,"randomBattleMoves":["bulkup","milkdrink","return","earthquake"],"randomBattleLevel":80},"glasshot":{"tier":"LC","isNonstandard":null},"glassannon":{"tier":"UUBL","isNonstandard":null,"randomBattleMoves":["icebeam","ironhead","thunderbolt","fireblast","earthquake"],"randomBattleLevel":76},"fluffyeti":{"tier":"LC","isNonstandard":null},"yedoom":{"tier":"RU","isNonstandard":null,"randomBattleMoves":["swordsdance","suckerpunch","iceshard","iciclecrash","closecombat","knockoff"],"randomBattleLevel":84},"mirrostine":{"tier":"UU","isNonstandard":null,"randomBattleMoves":["recover","willowisp","hex","focusblast","teleport"],"randomBattleLevel":84},"mudpants":{"tier":"LC","isNonstandard":null},"mudslacks":{"tier":"UU","isNonstandard":null,"randomBattleMoves":["swordsdance","highjumpkick","precipiceblades","volttackle","rapidspin"],"randomBattleLevel":84},"bukitlee":{"tier":"LC","isNonstandard":null},"lossolith":{"tier":"RU","isNonstandard":null,"randomBattleMoves":["wish","protect","toxic","psywave","stealthrock","teleport"],"randomBattleLevel":76},"mimimie":{"tier":"UU","isNonstandard":null,"randomBattleMoves":["waterspout","darkpulse","sludgebomb","icebeam","scald","lactoseshot"],"randomBattleLevel":80},"sprucifix":{"tier":"NU","isNonstandard":null,"randomBattleMoves":["recover","powerwhip","spikyshield","spikes","toxic"],"randomBattleLevel":80},"hulkan":{"tier":"UU","isNonstandard":null,"randomBattleMoves":["hulkup","closecombat","knockoff","facade","ironhead"],"randomBattleLevel":80},"nonite":{"tier":"LC","isNonstandard":null},"nonegative":{"tier":"NU","isNonstandard":null},"nomaestro":{"tier":"UU","isNonstandard":null,"randomBattleMoves":["boomburst","hurricane","earthquake","uturn","trick"],"randomBattleLevel":80},"dunkypea":{"tier":"LC","isNonstandard":null},"burdmen":{"tier":"NFE","isNonstandard":null},"nutzboltz":{"tier":"UU","isNonstandard":null,"randomBattleMoves":["oblivionwing","nastyplot","roost","flamethrower","taunt"],"randomBattleLevel":84},"kuklux":{"tier":"LC","isNonstandard":null},"kuklan":{"tier":"UU","isNonstandard":null,"randomBattleMoves":["blueflare","nastyplot","earthpower","willowisp","fierydance","grassknot"],"randomBattleLevel":82},"flameboyan":{"tier":"NUBL","isNonstandard":null,"randomBattleMoves":["moonblast","fierydance","earthpower","toke","moonlight"],"randomBattleLevel":84},"piicee":{"tier":"OU","isNonstandard":null,"randomBattleMoves":["dailydose","wish","protect","teleport","psychoboost"],"randomBattleLevel":84},"sonnanos":{"tier":"RU","isNonstandard":null,"randomBattleMoves":["doubleironbash","superpower","thunderpunch","teleport","knockoff"],"randomBattleLevel":84},"plebbles":{"tier":"NU","isNonstandard":null,"randomBattleMoves":["stealthrock","glare","spikes","rockslide","earthquake"],"randomBattleLevel":84},"sapleaf":{"tier":"LC","isNonstandard":null},"ignut":{"tier":"NFE","isNonstandard":null},"phantash":{"tier":"NU","isNonstandard":null,"randomBattleMoves":["trickroom","moongeistbeam","focusblast","spore","nastyplot"],"randomBattleLevel":84},"polossus":{"tier":"NU","isNonstandard":null,"randomBattleMoves":["recover","gunkshot","toxicspikes","earthquake","clearsmog"],"randomBattleLevel":84},"hitmonana":{"tier":"RU","isNonstandard":null,"randomBattleMoves":["stealthrock","partingshot","closecombat","woodhammer","synthesis","spikes"],"randomBattleLevel":84},"ballacle":{"tier":"LC","isNonstandard":null},"barbarkley":{"tier":"OU","isNonstandard":null,"randomBattleMoves":["chaosdunk","closecombat","stealthrock","rapidspin","knockoff"],"randomBattleLevel":76},"kekroach":{"tier":"LC","isNonstandard":null},"rekroach":{"tier":"RU","isNonstandard":null,"randomBattleMoves":["partingshot","suckerpunch","firstimpression","uturn","closecombat","knockoff"],"randomBattleLevel":84},"ricosheep":{"tier":"LC","isNonstandard":null},"ricosuave":{"tier":"UU","isNonstandard":null,"randomBattleMoves":["uturn","headcharge","rapidspin","thunderwave","healingwish","taunt"],"randomBattleLevel":80},"spaghefant":{"tier":"OU","isNonstandard":null,"randomBattleMoves":["moonblast","earthpower","softboiled","stealthrock","mop"],"randomBattleLevel":84},"crystaquil":{"tier":"LC","isNonstandard":null},"crystaking":{"tier":"OU","isNonstandard":null,"randomBattleMoves":["gunkshot","iciclecrash","earthquake","swordsdance","rapidspin"],"randomBattleLevel":84},"fontaba":{"tier":"OU","isNonstandard":null,"randomBattleMoves":["lightscreen","reflect","teleport","taunt","psychoboost"],"randomBattleLevel":84},"fontabab":{"tier":"NU","isNonstandard":null},"fontabac":{"tier":"RU","isNonstandard":null},"fontabaco":{"tier":"RU","isNonstandard":null},"fontabad":{"tier":"RU","isNonstandard":null},"fontabaf":{"tier":"RU","isNonstandard":null},"fontabafa":{"tier":"RU","isNonstandard":null},"fontabafit":{"tier":"RU","isNonstandard":null},"fontabag":{"tier":"RU","isNonstandard":null},"fontabah":{"tier":"RU","isNonstandard":null},"fontabaint":{"tier":"UU","isNonstandard":null},"fontabajp":{"tier":"RU","isNonstandard":null},"fontabak":{"tier":"RUBL","isNonstandard":null},"fontabaout":{"tier":"RU","isNonstandard":null},"fontabapol":{"tier":"UUBL","isNonstandard":null},"fontabar9k":{"tier":"RU","isNonstandard":null},"fontaba5":{"tier":"NU","isNonstandard":null},"fontabas4s":{"tier":"RU","isNonstandard":null},"fontabasoc":{"tier":"RU","isNonstandard":null},"fontabasp":{"tier":"RU","isNonstandard":null},"fontabatrv":{"tier":"RU","isNonstandard":null},"fontabatv":{"tier":"RU","isNonstandard":null},"fontabav":{"tier":"RU","isNonstandard":null},"fontabavg":{"tier":"RU","isNonstandard":null},"fontabavp":{"tier":"RU","isNonstandard":null},"fontabavr":{"tier":"RU","isNonstandard":null},"fontabax":{"tier":"RU","isNonstandard":null},"fontabaz":{"tier":"Uber","isNonstandard":null},"floconut":{"tier":"LC","isNonstandard":null},"sappalm":{"tier":"NFE","isNonstandard":null},"roynapalm":{"tier":"OU","isNonstandard":null,"randomBattleMoves":["sunnyday","gigadrain","fireblast","earthpower","growth"],"randomBattleLevel":84},"manateet":{"tier":"LC","isNonstandard":null},"manatorque":{"tier":"NFE","isNonstandard":null},"manatank":{"tier":"OU","isNonstandard":null,"randomBattleMoves":["milkdrink","liquidation","iciclecrash","earthquake","aquajet","spikes"],"randomBattleLevel":76},"anonymouse":{"tier":"NU","isNonstandard":null,"randomBattleMoves":["voltswitch","volttackle","owtheedge","suckerpunch","swordsdance"],"randomBattleLevel":84},"motherfuck":{"tier":"UU","isNonstandard":null,"randomBattleMoves":["spore","stealthrock","uturn","roost","earthquake"],"randomBattleLevel":80},"ninoop":{"tier":"LC","isNonstandard":null},"draconius":{"tier":"OU","isNonstandard":null,"randomBattleMoves":["dragondance","return","earthquake","roost","dragonclaw"],"randomBattleLevel":76},"ticktac":{"tier":"LC","isNonstandard":null},"eareticle":{"tier":"NFE","isNonstandard":null},"scythear":{"tier":"RUBL","isNonstandard":null,"randomBattleMoves":["swordsdance","ironhead","rockslide","earthquake","uturn"],"randomBattleLevel":80},"cozload":{"tier":"LC","isNonstandard":null},"snugware":{"tier":"RU","isNonstandard":null,"randomBattleMoves":["nuzzle","plasmafists","recover","uturn"],"randomBattleLevel":84},"fleespecs":{"tier":"UU","isNonstandard":null,"randomBattleMoves":["voltswitch","thunderbolt","bugbuzz","energyball","trick"],"randomBattleLevel":80},"honrade":{"tier":"RU","isNonstandard":null,"randomBattleMoves":["pixiepummel","sacredsword","earthquake","swordsdance","1000folds"],"randomBattleLevel":80},"embortion":{"tier":"NFE","isNonstandard":null},"premantom":{"tier":"NUBL","isNonstandard":null,"randomBattleMoves":["hex","darkpulse","willowisp","softboiled"],"randomBattleLevel":80},"galavik":{"tier":"LC","isNonstandard":null},"galavire":{"tier":"OU","isNonstandard":null,"randomBattleMoves":["thunderbolt","flashcannon","overheat","voltswitch","energyball"],"randomBattleLevel":76},"galaviste":{"tier":"OU","isNonstandard":null,"randomBattleMoves":["punchout","doubleironbash","superpower","plasmafists","thunderwave"],"randomBattleLevel":76},"pollefin":{"tier":"LC","isNonstandard":null},"florigrace":{"tier":"OU","isNonstandard":null,"randomBattleMoves":["spore","sleazyspores","mop","seedflare","scald","softboiled"],"randomBattleLevel":80},"lasslee":{"tier":"LC","isNonstandard":null},"wifemin":{"tier":"RU","isNonstandard":null,"randomBattleMoves":["teleport","psychic","mop","softboiled","lovelykiss"],"randomBattleLevel":84},"uwotto":{"tier":"RUBL","isNonstandard":null,"randomBattleMoves":["shiftgear","meteormash","psychicfangs","earthquake","hypnosis"],"randomBattleLevel":80},"venowatt":{"tier":"Uber","isNonstandard":null,"randomBattleMoves":["roost","paraboliccharge","tailglow","sludgebomb","gigadrain"],"randomBattleLevel":76},"vaultevour":{"tier":"RUBL","isNonstandard":null,"randomBattleMoves":["crunch","ironhead","stealthrock","suckerpunch","swordsdance"],"randomBattleLevel":80},"semdemen":{"tier":"OU","isNonstandard":null,"randomBattleMoves":["scald","earthquake","softboiled","stealthrock","stickyweb"],"randomBattleLevel":76},"dragking":{"tier":"RU","isNonstandard":null,"randomBattleMoves":["pixiepummel","highjumpkick","earthquake","uturn","trick","blazekick"],"randomBattleLevel":84},"kuuroba":{"tier":"Uber","isNonstandard":null,"randomBattleMoves":["closecombat","futababreak","stoneedge","speedweed","zenheadbutt"],"randomBattleLevel":72},"baitmaster":{"tier":"OU","isNonstandard":null,"randomBattleMoves":["scald","moonblast","nastyplot","stealthrock","psychic","uturn"],"randomBattleLevel":76},"spookster":{"tier":"LC","isNonstandard":null},"spookeer":{"tier":"NFE","isNonstandard":null},"spookzilla":{"tier":"OU","isNonstandard":null,"randomBattleMoves":["spookout","shadowsneak","shadowbone","superpower","glare"],"randomBattleLevel":76},"derpato":{"tier":"LC","isNonstandard":null},"retater":{"tier":"NU","isNonstandard":null},"potarded":{"tier":"OU","isNonstandard":null,"randomBattleMoves":["earthquake","toxic","softboiled","stealthrock","stoneedge"],"randomBattleLevel":76},"sadfish":{"tier":"UU","isNonstandard":null,"randomBattleMoves":["sudoku","scald","mop","foulplay","magiccoat"],"randomBattleLevel":80},"deloris":{"tier":"NU","isNonstandard":null,"randomBattleMoves":["geomancy","fizzbitch","shadowball","hiddenpowerfighting","softboiled"],"randomBattleLevel":84},"oreon":{"tier":"OU","isNonstandard":null,"randomBattleMoves":["baddybad","moonblast","lightscreen","trick","milkdrink"],"randomBattleLevel":76},"farfigtron":{"tier":"OU","isNonstandard":null,"randomBattleMoves":["firebomb","closecombat","earthquake","partingshot","swordsdance"],"randomBattleLevel":80},"regirode":{"tier":"RU","isNonstandard":null,"randomBattleMoves":["earthpower","calmmind","spooperpower","focusblast","erosionwave"],"randomBattleLevel":84},"regimelt":{"tier":"UU","isNonstandard":null,"randomBattleMoves":["spooperpower","iciclecrash","superpower","shadowsneak","earthquake"],"randomBattleLevel":84},"regirust":{"tier":"RU","isNonstandard":null,"randomBattleMoves":["spooperpower","closecombat","ironhead","stealthrock","willowisp"],"randomBattleLevel":84},"vivaiger":{"tier":"Uber","isNonstandard":null,"randomBattleMoves":["overenergize","overheat","voltswitch","earthpower","hiddenpowerice"],"randomBattleLevel":72},"heliofug":{"tier":"Uber","isNonstandard":null,"randomBattleMoves":["dracometeor","dragonclaw","vcreate","extremespeed","earthquake"],"randomBattleLevel":72},"sadrog":{"tier":"LC","isNonstandard":null},"smugrok":{"tier":"NFE","isNonstandard":null},"peperee":{"tier":"UU","isNonstandard":null,"randomBattleMoves":["greatrage","stealthrock","slackoff","stoneedge","earthquake"],"randomBattleLevel":80},"hodtog":{"tier":"LC","isNonstandard":null},"wienebark":{"tier":"NFE","isNonstandard":null},"saudoge":{"tier":"UU","isNonstandard":null,"randomBattleMoves":["wowwiener","aeroblast","uturn","earthpower","focusblast"],"randomBattleLevel":76},"gnarrk":{"tier":"LC","isNonstandard":null},"corsharrk":{"tier":"NFE","isNonstandard":null},"davyjaws":{"tier":"OU","isNonstandard":null,"randomBattleMoves":["closecombat","plunder","partingshot","earthquake","trick"],"randomBattleLevel":80},"humpunny":{"tier":"LC","isNonstandard":null},"bunnorgy":{"tier":"RUBL","isNonstandard":null,"randomBattleMoves":["fakeout","quickattack","return","knockoff","highjumpkick"],"randomBattleLevel":80},"emelgy":{"tier":"LC","isNonstandard":null},"fedorawk":{"tier":"NFE","isNonstandard":null},"fazeagle":{"tier":"UU","isNonstandard":null,"randomBattleMoves":["toke","aeroblast","searingshot","focusblast"],"randomBattleLevel":80},"catikillar":{"tier":"LC","isNonstandard":null},"tikoon":{"tier":"NFE","isNonstandard":null},"oogabuga":{"tier":"RU","isNonstandard":null,"randomBattleMoves":["quiverdance","seedflare","bugbuzz","focusblast","roost"],"randomBattleLevel":84},"ebining":{"tier":"LC","isNonstandard":null},"emplyin":{"tier":"OU","isNonstandard":null,"randomBattleMoves":["knockoff","closecombat","gunkshot","suckerpunch","pursuit"],"randomBattleLevel":76},"upbote":{"tier":"LC","isNonstandard":null},"upbeddit":{"tier":"RU","isNonstandard":null,"randomBattleMoves":["mop","recover","psystrike","teleport","toxic"],"randomBattleLevel":84},"flipbird":{"tier":"LC","isNonstandard":null},"wheygle":{"tier":"RU","isNonstandard":null,"randomBattleMoves":["uturn","acrobatics","drainpunch","substitute"],"randomBattleLevel":80},"gangnome":{"tier":"UU","isNonstandard":null,"randomBattleMoves":["toxic","protect","lunardance","foulplay","teleport"],"randomBattleLevel":84},"pyongnome":{"tier":"NU","isNonstandard":null,"randomBattleMoves":["meteormash","superpower","baddybad","thunderbolt","trick"],"randomBattleLevel":84},"bruhkid":{"tier":"LC","isNonstandard":null},"ubruh":{"tier":"UU","isNonstandard":null,"randomBattleMoves":["shoreup","closecombat","thousandwaves","drainpunch","stoneedge"],"randomBattleLevel":84},"walruse":{"tier":"LC","isNonstandard":null},"walruskie":{"tier":"NU","isNonstandard":null,"randomBattleMoves":["liquidation","meteormash","icehammer","bulletpunch","bellydrum","earthquake"],"randomBattleLevel":84},"diobat":{"tier":"LC","isNonstandard":null},"warudio":{"tier":"OU","isNonstandard":null,"randomBattleMoves":["knockoff","closecombat","uturn","pursuit","suckerpunch"],"randomBattleLevel":76},"docee":{"tier":"LC","isNonstandard":null},"donutsteel":{"tier":"RU","isNonstandard":null,"randomBattleMoves":["geomancy","flashcannon","focusblast","baddybad"],"randomBattleLevel":80},"cakupple":{"tier":"LC","isNonstandard":null},"fondupple":{"tier":"UU","isNonstandard":null,"randomBattleMoves":["milkdrink","pixiepummel","powerwhip","leechseed","aromatherapy"],"randomBattleLevel":84},"baloofang":{"tier":"NU","isNonstandard":null,"randomBattleMoves":["hex","willowisp","roost","spectralthief","focusblast"],"randomBattleLevel":80},"socckat":{"tier":"NUBL","isNonstandard":null,"randomBattleMoves":["highjumpkick","return","uturn","fakeout","swordsdance"],"randomBattleLevel":80},"egylamp":{"tier":"LC","isNonstandard":null},"ruselamp":{"tier":"OU","isNonstandard":null,"randomBattleMoves":["thunderbolt","psychic","fireblast","voltswitch","trick"],"randomBattleLevel":76},"mehndior":{"tier":"LC","isNonstandard":null},"tunakking":{"tier":"RUBL","isNonstandard":null,"randomBattleMoves":["fierydance","psyshock","uturn","trick","earthpower"],"randomBattleLevel":84},"missletoe":{"tier":"LC","isNonstandard":null},"hohohoming":{"tier":"RUBL","isNonstandard":null,"randomBattleMoves":["frostbreath","earthpower","focusblast","uturn","freezedry"],"randomBattleLevel":80},"flaa":{"tier":"LC","isNonstandard":null},"hopault":{"tier":"UU","isNonstandard":null,"randomBattleMoves":["highjumpkick","uturn","megakick","knockoff","rapidspin"],"randomBattleLevel":80},"araketsu":{"tier":"LC","isNonstandard":null},"senketula":{"tier":"RU","isNonstandard":null,"randomBattleMoves":["stickyweb","knockoff","uturn","pursuit","spikes","gunkshot"],"randomBattleLevel":84},"falcaptain":{"tier":"RUBL","isNonstandard":null,"randomBattleMoves":["falconpunch","closecombat","knockoff","bulkup","roost"],"randomBattleLevel":76},"cirpent":{"tier":"LC","isNonstandard":null},"traumobra":{"tier":"OU","isNonstandard":null,"randomBattleMoves":["glare","encore","moonblast","sludgebomb","lovelykiss"],"randomBattleLevel":76},"lizascoop":{"tier":"LC","isNonstandard":null},"reptrill":{"tier":"NU","isNonstandard":null,"randomBattleMoves":["ironhead","earthquake","stoneedge","stealthrock","quicksand"],"randomBattleLevel":84},"fefeion":{"tier":"LC","isNonstandard":null},"feferun":{"tier":"RU","isNonstandard":null,"randomBattleMoves":["earthpower","fierydance","morningsun","thunderbolt","scorchedearth"],"randomBattleLevel":84},"jerkle":{"tier":"NU","isNonstandard":null,"randomBattleMoves":["trickroom","photongeyser","earthpower","powergem","nastyplot"],"randomBattleLevel":84},"faptime":{"tier":"UU","isNonstandard":null,"randomBattleMoves":["swordsdance","photongeyser","stoneedge","earthquake","accelerock"],"randomBattleLevel":84},"shiriman":{"tier":"RU","isNonstandard":null,"randomBattleMoves":["glare","softboiled","pixiepummel","teleport","willowisp"],"randomBattleLevel":84},"fresrye":{"tier":"LC","isNonstandard":null},"dedwheat":{"tier":"RU","isNonstandard":null,"randomBattleMoves":["skillswap","leechseed","protect","spore","sludgebomb"],"randomBattleLevel":80},"spargle":{"tier":"LC","isNonstandard":null},"spedo":{"tier":"RU","isNonstandard":null,"randomBattleMoves":["bulkup","playrough","suckerpunch","slackoff","earthquake"],"randomBattleLevel":84},"housant":{"tier":"LC","isNonstandard":null},"apartmant":{"tier":"OU","isNonstandard":null,"randomBattleMoves":["shellsmash","attackorder","stoneedge","earthquake"],"randomBattleLevel":80},"fuermiga":{"tier":"LC","isNonstandard":null},"maripyro":{"tier":"OU","isNonstandard":null,"randomBattleMoves":["flareblitz","overbite","uturn","roost","willowisp"],"randomBattleLevel":76},"confirmabi":{"tier":"OU","isNonstandard":null,"randomBattleMoves":["nastyplot","leafstorm","earthpower","psychic","recover"],"randomBattleLevel":76},"bulbapedo":{"tier":"NU","isNonstandard":null,"randomBattleMoves":["leechseed","gunkshot","softboiled","clearsmog","gigadrain"],"randomBattleLevel":84},"wastenaut":{"tier":"LC","isNonstandard":null},"wantnaut":{"tier":"RU","isNonstandard":null,"randomBattleMoves":["stealthrock","slackoff","toxicspikes","gunkshot","earthquake","heavyslam"],"randomBattleLevel":84},"cansumor":{"tier":"UU","isNonstandard":null,"randomBattleMoves":["toxic","softboiled","nightshade","teleport","gunkshot"],"randomBattleLevel":76},"snuffant":{"tier":"LC","isNonstandard":null},"cokemmoth":{"tier":"NU","isNonstandard":null,"randomBattleMoves":["auroraveil","iciclecrash","earthquake","swordsdance","sleeppowder"],"randomBattleLevel":84},"grimdak":{"tier":"UU","isNonstandard":null,"randomBattleMoves":["owtheedge","1000folds","suckerpunch","protect","substitute"],"randomBattleLevel":80},"shroofle":{"tier":"UU","isNonstandard":null,"randomBattleMoves":["foulplay","spore","softboiled","toxicspikes","protect"],"randomBattleLevel":80},"betacluck":{"tier":"LC","isNonstandard":null},"thundacock":{"tier":"OU","isNonstandard":null,"randomBattleMoves":["volttackle","bravebird","closecombat","voltswitch","defog"],"randomBattleLevel":80},"twinfowl":{"tier":"LC","isNonstandard":null},"avianjoin":{"tier":"UU","isNonstandard":null,"randomBattleMoves":["heavyslam","heatcrash","roost","bravebird","bulkup"],"randomBattleLevel":80},"illuminowl":{"tier":"LC","isNonstandard":null},"illumatrix":{"tier":"OU","isNonstandard":null,"randomBattleMoves":["psychoboost","aeroblast","heatwave","earthpower","uturn"],"randomBattleLevel":76},"typobop":{"tier":"LC","isNonstandard":null},"yeerex":{"tier":"NU","isNonstandard":null,"randomBattleMoves":["dragondance","knockoff","stoneedge","zenheadbutt","suckerpunch"],"randomBattleLevel":84},"randomix":{"tier":"LC","isNonstandard":null},"cthullord":{"tier":"NU","isNonstandard":null,"randomBattleMoves":["shellsmash","originpulse","stoneedge","zenheadbutt"],"randomBattleLevel":80},"quiboom":{"tier":"LC","isNonstandard":null},"gynuke":{"tier":"UU","isNonstandard":null,"randomBattleMoves":["vcreate","waterfall","uturn","explosion"],"randomBattleLevel":80},"rainglock":{"tier":"UU","isNonstandard":null,"randomBattleMoves":["originpulse","icebeam","darkpulse","aurasphere","waterspout"],"randomBattleLevel":80},"beatmarine":{"tier":"LC","isNonstandard":null},"substarr":{"tier":"RUBL","isNonstandard":null,"randomBattleMoves":["boomburst","scald","discharge","healbell","slackoff","icebeam"],"randomBattleLevel":84},"hofucno":{"tier":"UU","isNonstandard":null,"randomBattleMoves":["spore","perishsong","airslash","roost","scald"],"randomBattleLevel":84},"hornigiri":{"tier":"LC","isNonstandard":null},"hornicier":{"tier":"NFE","isNonstandard":null},"hornititan":{"tier":"OU","isNonstandard":null,"randomBattleMoves":["iciclecrash","earthquake","stealthrock","rapidspin","glare","recover"],"randomBattleLevel":80},"preasu":{"tier":"LC","isNonstandard":null},"undastand":{"tier":"NU","isNonstandard":null,"randomBattleMoves":["boltstrike","icepunch","thunderwave","substitute","slackoff"],"randomBattleLevel":84},"warney":{"tier":"LC","isNonstandard":null},"banageddon":{"tier":"OU","isNonstandard":null,"randomBattleMoves":["banhammer","hammerarm","knockoff","partingshot","earthquake"],"randomBattleLevel":80},"acufront":{"tier":"UU","isNonstandard":null,"randomBattleMoves":["boomburst","voltswitch","fireblast","earthpower","hydropump"],"randomBattleLevel":76},"acufrontf":{"isNonstandard":null,"tier":"Illegal"},"acufrontw":{"isNonstandard":null,"tier":"Illegal"},"acufronti":{"isNonstandard":null,"tier":"Illegal"},"militant":{"tier":"OU","isNonstandard":null,"randomBattleMoves":["overbite","gunkshot","uturn","extremespeed","knockoff"],"randomBattleLevel":80},"shiggydig":{"tier":"UU","isNonstandard":null,"randomBattleMoves":["homerunbat","stealthrock","slackoff","earthquake","knockoff","stoneedge"],"randomBattleLevel":84},"signot":{"tier":"LC","isNonstandard":null},"reagain":{"tier":"OU","isNonstandard":null,"randomBattleMoves":["recover","knockoff","earthquake","toxic","stealthrock"],"randomBattleLevel":84},"ormite":{"tier":"LC","isNonstandard":null},"viristal":{"tier":"UU","isNonstandard":null,"randomBattleMoves":["trickroom","powergem","earthpower","thunderbolt","tailglow"],"randomBattleLevel":84},"rolango":{"tier":"LC","isNonstandard":null},"dreameme":{"tier":"OU","isNonstandard":null,"randomBattleMoves":["softboiled","spikes","defog","moonblast","teleport"],"randomBattleLevel":76},"pearchie":{"tier":"UU","isNonstandard":null,"randomBattleMoves":["softboiled","substitute","extremespeed","woodhammer","earthquake"],"randomBattleLevel":80},"tarditank":{"tier":"NUBL","isNonstandard":null,"randomBattleMoves":["rest","scald","infestation","toxic","powersplit"],"randomBattleLevel":84},"iplora":{"tier":"LC","isNonstandard":null},"pitayen":{"tier":"LC","isNonstandard":null},"dragaya":{"tier":"NFE","isNonstandard":null},"frutagon":{"tier":"OU","isNonstandard":null,"randomBattleMoves":["dragondance","dragonhammer","leafblade","earthquake","synthesis"],"randomBattleLevel":80},"biteki":{"tier":"NUBL","isNonstandard":null,"randomBattleMoves":["voltswitch","freezedry","earthpower","psychoboost","icebeam","heatwave"],"randomBattleLevel":84},"sesquatch":{"tier":"OU","isNonstandard":null,"randomBattleMoves":["bulkup","skullbash","shadowforce","slackoff","closecombat","spookout"],"randomBattleLevel":80},"fireshi":{"tier":"LC","isNonstandard":null},"fireshitwi":{"tier":"NFE","isNonstandard":null},"fireshitre":{"tier":"UUBL","isNonstandard":null,"randomBattleMoves":["calmmind","lavaplume","sludgebomb","morningsun","thunderbolt"],"randomBattleLevel":80},"slugbud":{"tier":"LC","isNonstandard":null},"slughug":{"tier":"NFE","isNonstandard":null},"slugfugg":{"tier":"OU","isNonstandard":null,"randomBattleMoves":["softboiled","liquidation","knockoff","toxic","haze","gunkshot"],"randomBattleLevel":76},"skeletroll":{"tier":"LC","isNonstandard":null},"spookscare":{"tier":"UU","isNonstandard":null,"randomBattleMoves":["stealthrock","earthpower","willowisp","recover","shadowball"],"randomBattleLevel":80},"goryannus":{"tier":"Uber","isNonstandard":null,"randomBattleMoves":["shadowbone","earthquake","spookout","shadowsneak","playrough"],"randomBattleLevel":76},"lankong":{"tier":"LC","isNonstandard":null},"ballankey":{"tier":"NFE","isNonstandard":null},"funnedong":{"tier":"Uber","isNonstandard":null,"randomBattleMoves":["return","closecombat","uturn","bulkup","knockoff"],"randomBattleLevel":72},"narwhiz":{"tier":"Uber","isNonstandard":null,"randomBattleMoves":["softboiled","haze","moonblast","scald","teleport"],"randomBattleLevel":72},"niterpent":{"tier":"Uber","doublesTier":"DUber","isNonstandard":null,"randomBattleMoves":["blueflare","thunderbolt","hiddenpowerice","voltswitch","boltstrike"],"randomBattleLevel":76},"griffawork":{"tier":"Uber","isNonstandard":null,"randomBattleMoves":["calmmind","roost","aeroblast","psystrike","focusblast"],"randomBattleLevel":72},"boarnograf":{"tier":"Uber","isNonstandard":null,"randomBattleMoves":["foulplay","overheat","haze","gunkshot"],"randomBattleLevel":72},"admoot":{"tier":"OU","isNonstandard":null,"randomBattleMoves":["milkdrink","moonblast","flamethrower","earthpower","nastyplot"],"randomBattleLevel":80},"tentaquil":{"tier":"Uber","isNonstandard":null,"randomBattleMoves":["shellsmash","spore","pukeblood","psystrike","vcreate"],"randomBattleLevel":72},"hailsanta":{"tier":"Uber","randomBattleMoves":["slipturn","icebeam","earthpower","knockoff","milkdrink"],"isNonstandard":null},"blobbos":{"tier":"LC","isNonstandard":null,"randomBattleMoves":["supersnore","stoneedge","mindreader","sheercold","transform"],"randomBattleLevel":100},"vandash":{"tier":"RU","isNonstandard":null,"randomBattleMoves":["kingsshield","leechseed","substitute","metronome"],"randomBattleLevel":84},"nutjobber":{"tier":"NFE","isNonstandard":null},"deisnutz":{"tier":"NU","isNonstandard":null,"randomBattleMoves":["leechseed","substitute","pixiepummel","taunt","softboiled"],"randomBattleLevel":84},"adesign":{"tier":"Uber","isNonstandard":null,"randomBattleMoves":["anattack","teleport","softboiled","defog","stealthrock"],"randomBattleLevel":72},"clovenix":{"tier":"Uber","isNonstandard":null,"randomBattleMoves":["tailwind","energyball","fireblast","defog","earthpower"],"randomBattleLevel":72},"jewipede":{"tier":"Uber","isNonstandard":null,"randomBattleMoves":["swordsdance","extremespeed","spectralthief","lovelykiss","uturn"],"randomBattleLevel":72}}